setup.py
easy_rest.egg-info/PKG-INFO
easy_rest.egg-info/SOURCES.txt
easy_rest.egg-info/dependency_links.txt
easy_rest.egg-info/not-zip-safe
easy_rest.egg-info/requires.txt
easy_rest.egg-info/top_level.txt
easyapi/__init__.py
easyapi/decorators.py
easyapi/encoder.py
easyapi/enums.py
easyapi/errors.py
easyapi/fields.py
easyapi/filters.py
easyapi/middleware.py
easyapi/paginator.py
easyapi/params.py
easyapi/permissions.py
easyapi/router.py
easyapi/serializer.py
easyapi/utils.py
easyapi/viewsets.py
easyapi/tests/__init__.py
easyapi/tests/conftest.py
easyapi/tests/factories.py
easyapi/tests/fixtures.py
easyapi/tests/generate_data.py
easyapi/tests/test_auto_router.py
easyapi/tests/test_decorators.py
easyapi/tests/test_embedded.py
easyapi/tests/test_enums.py
easyapi/tests/test_extract_params.py
easyapi/tests/test_filtering.py
easyapi/tests/test_instance_method_property.py
easyapi/tests/test_manager_method.py
easyapi/tests/test_meta.py
easyapi/tests/test_pagination.py
easyapi/tests/test_reverse_relations.py
easyapi/tests/test_security.py
easyapi/tests/test_standard.py
easyapi/tests/test_project/__init__.py
easyapi/tests/test_project/api.py
easyapi/tests/test_project/manage.py
easyapi/tests/test_project/models.py
easyapi/tests/test_project/settings.py
easyapi/tests/test_project/urls.py
easyapi/tests/test_project/views.py
easyapi/tests/test_project/wsgi.py