Metadata-Version: 1.1
Name: easy-rest
Version: 0.4.1
Summary: Real Python Enums for Django.
Home-page: https://github.com/mturilin/easyapi
Author: mturilin
Author-email: mturilin@gmail.com
License: MIT
Platform: UNKNOWN
Classifier: Environment :: Web Environment
Classifier: Framework :: Django
Classifier: Intended Audience :: Developers
Classifier: Operating System :: OS Independent
Classifier: Programming Language :: Python
Classifier: Topic :: Internet :: WWW/HTTP
